lib_ml_team11/__init__.py
lib_ml_team11/preprocessing.py
lib_ml_team11-0.0.1.dist-info/METADATA
lib_ml_team11-0.0.1.dist-info/WHEEL
lib_ml_team11-0.0.1.dist-info/RECORD
