Metadata-Version: 2.1
Name: lib-ml-team11
Version: 0.0.1
Summary: Contains the pre-processing logic for data that is used for training or queries.
Author: team_11
Author-email: E.Sipols@student.tudelft.nl
Requires-Python: >=3.11,<4.0
Classifier: Programming Language :: Python :: 3
Classifier: Programming Language :: Python :: 3.11
Classifier: Programming Language :: Python :: 3.12
Requires-Dist: keras (==3.3.3)
Requires-Dist: scikit-learn (==1.4.2)
Requires-Dist: tensorflow (==2.16.1)
